liitos/__init__.py
liitos/__main__.py
liitos/approvals.py
liitos/captions.py
liitos/changes.py
liitos/cli.py
liitos/concat.py
liitos/description_lists.py
liitos/eject.py
liitos/figures.py
liitos/gather.py
liitos/labels.py
liitos/liitos.py
liitos/meta.py
liitos/patch.py
liitos/placeholder.py
liitos/render.py
liitos/tables.py
liitos/template.py
liitos/tools.py
liitos/placeholders/this-resource-is-missing.jpg
liitos/placeholders/this-resource-is-missing.pdf
liitos/placeholders/this-resource-is-missing.png
liitos/placeholders/this-resource-is-missing.svg
liitos/placeholders/this-resource-is-missing.tiff
liitos/placeholders/this-resource-is-missing.webp
liitos/templates/approvals.yml
liitos/templates/bookmatter.tex.in
liitos/templates/changes.yml
liitos/templates/driver.tex.in
liitos/templates/layout.yml
liitos/templates/meta-patch.yml
liitos/templates/meta.yml
liitos/templates/metadata.tex.in
liitos/templates/mkdocs.yml.in
liitos/templates/publisher.tex.in
liitos/templates/setup.tex.in
liitos/templates/vocabulary.yml
liitos-2025.10.14.dist-info/licenses/LICENSE
liitos-2025.10.14.dist-info/METADATA
liitos-2025.10.14.dist-info/WHEEL
liitos-2025.10.14.dist-info/entry_points.txt
liitos-2025.10.14.dist-info/top_level.txt
liitos-2025.10.14.dist-info/RECORD
