Metadata-Version: 2.4
Name: liitos
Version: 2025.10.14
Summary: Splice (Finnish liitos) contributions.
Author-email: Stefan Hagen <stefan@hagen.link>
Maintainer-email: Stefan Hagen <stefan@hagen.link>
License-Expression: MIT
Project-URL: Homepage, https://git.sr.ht/~sthagen/liitos
Project-URL: Bug-Tracker, https://todo.sr.ht/~sthagen/liitos
Project-URL: Documentation, https://codes.dilettant.life/docs/liitos
Project-URL: Source-Code, https://git.sr.ht/~sthagen/liitos
Project-URL: Test-Coverage, https://codes.dilettant.life/coverage/liitos
Keywords: developer-tools,validation,verification
Classifier: Development Status :: 4 - Beta
Classifier: Intended Audience :: Developers
Classifier: Programming Language :: Python :: 3.10
Classifier: Programming Language :: Python :: 3.11
Classifier: Programming Language :: Python :: 3.12
Classifier: Programming Language :: Python :: 3.13
Classifier: Programming Language :: Python :: 3.9
Requires-Python: >=3.9
License-File: LICENSE
Requires-Dist: PyYAML>=6.0.3
Requires-Dist: foran>=2023.6.19
Requires-Dist: platformdirs>=4.5.0
Requires-Dist: shellingham>=1.5.4
Requires-Dist: taksonomia>=2023.6.18
Requires-Dist: treelib>=1.8.0
Requires-Dist: typer>=0.19.2
Provides-Extra: dev
Requires-Dist: black; extra == "dev"
Requires-Dist: coverage; extra == "dev"
Requires-Dist: hypothesis; extra == "dev"
Requires-Dist: mypy; extra == "dev"
Requires-Dist: pytest; extra == "dev"
Requires-Dist: pytest-cov; extra == "dev"
Requires-Dist: pytest-flake8; extra == "dev"
Requires-Dist: ruff; extra == "dev"
Dynamic: license-file
